{
  "success": true,
  "games": {
    "MAIN_LOBBY": {
      "players": 527
    },
    "TOURNAMENT_LOBBY": {
      "players": 6
    },
    "SMP": {
      "players": 1263
    },
    "HOUSING": {
      "players": 1843
    },
    "PIT": {
      "players": 488,
      "modes": {
        "PIT": 488
      }
    },
    "TNTGAMES": {
      "players": 572,
      "modes": {
        "PVPRUN": 4,
        "TNTAG": 301,
        "TNTRUN": 117,
        "BOWSPLEEF": 30,
        "CAPTURE": 22
      }
    },
    "REPLAY": {
      "players": 52,
      "modes": {
        "BASE": 52
      }
    },
    "SURVIVAL_GAMES": {
      "players": 144,
      "modes": {
        "solo_normal": 74,
        "teams_normal": 46
      }
    },
    "BEDWARS": {
      "players": 17161,
      "modes": {
        "BEDWARS_TWO_FOUR": 746,
        "BEDWARS_FOUR_THREE": 2004,
        "BEDWARS_FOUR_FOUR_LUCKY": 2,
        "BEDWARS_EIGHT_ONE": 2635,
        "BEDWARS_EIGHT_TWO_VOIDLESS": 3,
        "BEDWARS_FOUR_FOUR_ARMED": 560,
        "BEDWARS_EIGHT_TWO_ARMED": 393,
        "BEDWARS_EIGHT_TWO": 5133,
        "BEDWARS_FOUR_FOUR": 2979,
        "BEDWARS_EIGHT_TWO_LUCKY": 21,
        "BEDWARS_PRACTICE": 410
      }
    },
    "SUPER_SMASH": {
      "players": 58,
      "modes": {
        "1v1_normal": 6,
        "solo_normal": 8,
        "2v2_normal": 8,
        "teams_normal": 2
      }
    },
    "SKYBLOCK": {
      "players": 29752,
      "modes": {
        "dungeon_hub": 1091,
        "farming_1": 290,
        "mining_2": 760,
        "mining_3": 2047,
        "combat_3": 1393,
        "dynamic": 11827,
        "crystal_hollows": 2017,
        "combat_1": 321,
        "foraging_1": 501,
        "hub": 6360,
        "combat_2": 178,
        "dungeon": 2805,
        "mining_1": 163
      }
    },
    "MURDER_MYSTERY": {
      "players": 970,
      "modes": {
        "MURDER_DOUBLE_UP": 257,
        "MURDER_INFECTION": 99,
        "MURDER_ASSASSINS": 67,
        "MURDER_CLASSIC": 404
      }
    },
    "LEGACY": {
      "players": 148,
      "modes": {
        "GINGERBREAD": 13,
        "QUAKECRAFT": 11,
        "WALLS": 26,
        "VAMPIREZ": 50,
        "ARENA": 0,
        "PAINTBALL": 11
      }
    },
    "SKYWARS": {
      "players": 3211,
      "modes": {
        "ranked_normal": 106,
        "solo_insane_tnt_madness": 22,
        "solo_insane_lucky": 130,
        "teams_insane_lucky": 75,
        "teams_insane": 281,
        "solo_normal": 923,
        "solo_insane_hunters_vs_beasts": 3,
        "solo_insane": 786,
        "teams_insane_tnt_madness": 3,
        "teams_normal": 307,
        "mega_normal": 2
      }
    },
    "UHC": {
      "players": 262,
      "modes": {
        "TEAMS": 115,
        "SOLO": 109
      }
    },
    "ARCADE": {
      "players": 1204,
      "modes": {
        "PARTY": 260,
        "HOLE_IN_THE_WALL": 9,
        "DEFENDER": 35,
        "MINI_WALLS": 28,
        "SIMON_SAYS": 41,
        "ZOMBIES_BAD_BLOOD": 25,
        "HIDE_AND_SEEK_PARTY_POOPER": 28,
        "DAYONE": 69,
        "DRAW_THEIR_THING": 27,
        "ZOMBIES_ALIEN_ARCADIUM": 75,
        "SOCCER": 19,
        "PVP_CTW": 124,
        "ENDER": 8,
        "THROW_OUT": 1,
        "STARWARS": 3,
        "DRAGONWARS2": 5,
        "ZOMBIES_DEAD_END": 153,
        "FARM_HUNT": 51,
        "HIDE_AND_SEEK_PROP_HUNT": 54
      }
    },
    "SPEED_UHC": {
      "players": 37,
      "modes": {
        "team_normal": 14,
        "solo_normal": 23
      }
    },
    "BUILD_BATTLE": {
      "players": 816,
      "modes": {
        "BUILD_BATTLE_SOLO_NORMAL_LATEST": 201,
        "BUILD_BATTLE_GUESS_THE_BUILD": 99,
        "BUILD_BATTLE_TEAMS_NORMAL": 275,
        "BUILD_BATTLE_SOLO_PRO": 41,
        "BUILD_BATTLE_SOLO_NORMAL": 111
      }
    },
    "DUELS": {
      "players": 3552,
      "modes": {
        "DUELS_BOWSPLEEF_DUEL": 18,
        "DUELS_BOW_DUEL": 21,
        "DUELS_UHC_FOUR": 24,
        "DUELS_MW_DUEL": 16,
        "DUELS_UHC_MEETUP": 34,
        "DUELS_BRIDGE_DOUBLES": 257,
        "DUELS_SW_DOUBLES": 83,
        "DUELS_UHC_DOUBLES": 35,
        "DUELS_BRIDGE_FOUR": 44,
        "DUELS_BRIDGE_3V3V3V3": 17,
        "DUELS_UHC_DUEL": 282,
        "DUELS_SUMO_DUEL": 187,
        "DUELS_OP_DOUBLES": 30,
        "DUELS_OP_DUEL": 57,
        "DUELS_MW_DOUBLES": 4,
        "DUELS_BLITZ_DUEL": 39,
        "DUELS_POTION_DUEL": 17,
        "DUELS_CLASSIC_DUEL": 218,
        "DUELS_COMBO_DUEL": 28,
        "DUELS_BRIDGE_DUEL": 1196,
        "DUELS_SW_DUEL": 256
      }
    },
    "PROTOTYPE": {
      "players": 366,
      "modes": {
        "TOWERWARS_SOLO": 21,
        "TOWERWARS_TEAM_OF_TWO": 5
      }
    },
    "BATTLEGROUND": {
      "players": 77,
      "modes": {
        "ctf_mini": 34,
        "domination": 6
      }
    },
    "MCGO": {
      "players": 95,
      "modes": {
        "normal": 37,
        "deathmatch": 28
      }
    },
    "WALLS3": {
      "players": 84,
      "modes": {
        "standard": 69
      }
    },
    "LIMBO": {
      "players": 340
    },
    "IDLE": {
      "players": 6783
    },
    "QUEUE": {
      "players": 0
    }
  },
  "playerCount": 69776
}