{
  "success": true,
  "games": {
    "MAIN_LOBBY": {
      "players": 562
    },
    "TOURNAMENT_LOBBY": {
      "players": 18
    },
    "SMP": {
      "players": 1659
    },
    "SPEED_UHC": {
      "players": 34,
      "modes": {
        "team_normal": 15,
        "solo_normal": 19
      }
    },
    "UHC": {
      "players": 374,
      "modes": {
        "TEAMS": 193,
        "SOLO": 134
      }
    },
    "LEGACY": {
      "players": 212,
      "modes": {
        "WALLS": 48,
        "VAMPIREZ": 45,
        "QUAKECRAFT": 15,
        "ARENA": 5,
        "PAINTBALL": 32,
        "GINGERBREAD": 18
      }
    },
    "ARCADE": {
      "players": 1930,
      "modes": {
        "PARTY": 425,
        "HOLE_IN_THE_WALL": 17,
        "DEFENDER": 53,
        "MINI_WALLS": 65,
        "SIMON_SAYS": 82,
        "ZOMBIES_BAD_BLOOD": 21,
        "HIDE_AND_SEEK_PARTY_POOPER": 41,
        "DAYONE": 94,
        "DRAW_THEIR_THING": 40,
        "ZOMBIES_ALIEN_ARCADIUM": 121,
        "ONEINTHEQUIVER": 16,
        "SOCCER": 38,
        "PVP_CTW": 189,
        "ENDER": 13,
        "THROW_OUT": 4,
        "STARWARS": 33,
        "DRAGONWARS2": 12,
        "ZOMBIES_DEAD_END": 272,
        "HIDE_AND_SEEK_PROP_HUNT": 90,
        "FARM_HUNT": 58
      }
    },
    "HOUSING": {
      "players": 2455
    },
    "BUILD_BATTLE": {
      "players": 1174,
      "modes": {
        "BUILD_BATTLE_SOLO_NORMAL_LATEST": 292,
        "BUILD_BATTLE_GUESS_THE_BUILD": 129,
        "BUILD_BATTLE_TEAMS_NORMAL": 382,
        "BUILD_BATTLE_SOLO_PRO": 73,
        "BUILD_BATTLE_SOLO_NORMAL": 165
      }
    },
    "REPLAY": {
      "players": 106,
      "modes": {
        "BASE": 106
      }
    },
    "DUELS": {
      "players": 4474,
      "modes": {
        "DUELS_BOWSPLEEF_DUEL": 49,
        "DUELS_BRIDGE_2V2V2V2": 11,
        "DUELS_BOW_DUEL": 14,
        "DUELS_UHC_FOUR": 29,
        "DUELS_MW_DUEL": 16,
        "DUELS_UHC_MEETUP": 56,
        "DUELS_BRIDGE_DOUBLES": 284,
        "DUELS_SW_DOUBLES": 95,
        "DUELS_UHC_DOUBLES": 40,
        "DUELS_BRIDGE_FOUR": 87,
        "DUELS_BRIDGE_3V3V3V3": 34,
        "DUELS_UHC_DUEL": 419,
        "DUELS_SUMO_DUEL": 205,
        "DUELS_OP_DOUBLES": 44,
        "DUELS_OP_DUEL": 77,
        "DUELS_MW_DOUBLES": 2,
        "DUELS_BLITZ_DUEL": 69,
        "DUELS_POTION_DUEL": 9,
        "DUELS_CLASSIC_DUEL": 261,
        "DUELS_COMBO_DUEL": 48,
        "DUELS_BRIDGE_DUEL": 1356,
        "DUELS_SW_DUEL": 378
      }
    },
    "BATTLEGROUND": {
      "players": 131,
      "modes": {
        "ctf_mini": 68,
        "team_deathmatch": 2
      }
    },
    "WALLS3": {
      "players": 145,
      "modes": {
        "standard": 117
      }
    },
    "PROTOTYPE": {
      "players": 519,
      "modes": {
        "TOWERWARS_SOLO": 68,
        "TOWERWARS_TEAM_OF_TWO": 16
      }
    },
    "SKYBLOCK": {
      "players": 34567,
      "modes": {
        "dungeon_hub": 1369,
        "farming_1": 373,
        "mining_2": 916,
        "mining_3": 2404,
        "combat_3": 1680,
        "crystal_hollows": 2266,
        "dynamic": 12705,
        "combat_1": 404,
        "foraging_1": 636,
        "hub": 7779,
        "combat_2": 189,
        "dungeon": 3608,
        "mining_1": 240
      }
    },
    "PIT": {
      "players": 631,
      "modes": {
        "PIT": 631
      }
    },
    "SURVIVAL_GAMES": {
      "players": 204,
      "modes": {
        "solo_normal": 93,
        "teams_normal": 75
      }
    },
    "MURDER_MYSTERY": {
      "players": 1184,
      "modes": {
        "MURDER_DOUBLE_UP": 284,
        "MURDER_INFECTION": 137,
        "MURDER_ASSASSINS": 52,
        "MURDER_CLASSIC": 528
      }
    },
    "SKYWARS": {
      "players": 4136,
      "modes": {
        "ranked_normal": 137,
        "solo_insane_tnt_madness": 46,
        "solo_insane_lucky": 178,
        "solo_insane_slime": 5,
        "teams_insane_lucky": 99,
        "solo_normal": 1050,
        "teams_insane": 447,
        "solo_insane": 1051,
        "teams_insane_tnt_madness": 1,
        "teams_normal": 429,
        "mega_normal": 30
      }
    },
    "BEDWARS": {
      "players": 22134,
      "modes": {
        "BEDWARS_TWO_FOUR": 891,
        "BEDWARS_FOUR_FOUR_RUSH": 3,
        "BEDWARS_EIGHT_ONE": 3186,
        "BEDWARS_EIGHT_TWO_VOIDLESS": 6,
        "BEDWARS_FOUR_FOUR_ARMED": 814,
        "BEDWARS_EIGHT_TWO_ARMED": 618,
        "BEDWARS_FOUR_FOUR": 4046,
        "BEDWARS_EIGHT_TWO": 6419,
        "BEDWARS_EIGHT_TWO_LUCKY": 48,
        "BEDWARS_PRACTICE": 533,
        "BEDWARS_FOUR_THREE": 2721,
        "BEDWARS_FOUR_FOUR_LUCKY": 2,
        "BEDWARS_EIGHT_TWO_ULTIMATE": 6
      }
    },
    "MCGO": {
      "players": 133,
      "modes": {
        "normal": 59,
        "normal_party": 9,
        "deathmatch": 42
      }
    },
    "TNTGAMES": {
      "players": 770,
      "modes": {
        "PVPRUN": 24,
        "TNTAG": 353,
        "TNTRUN": 192,
        "CAPTURE": 31,
        "BOWSPLEEF": 38
      }
    },
    "SUPER_SMASH": {
      "players": 82,
      "modes": {
        "1v1_normal": 6,
        "solo_normal": 17,
        "2v2_normal": 24
      }
    },
    "LIMBO": {
      "players": 455
    },
    "IDLE": {
      "players": 8811
    },
    "QUEUE": {
      "players": 0
    }
  },
  "playerCount": 86890
}