{
  "success": true,
  "games": {
    "MAIN_LOBBY": {
      "players": 476
    },
    "TOURNAMENT_LOBBY": {
      "players": 9
    },
    "SMP": {
      "players": 1136
    },
    "SPEED_UHC": {
      "players": 60,
      "modes": {
        "team_normal": 25,
        "solo_normal": 35
      }
    },
    "UHC": {
      "players": 493,
      "modes": {
        "TEAMS": 277,
        "SOLO": 163
      }
    },
    "LEGACY": {
      "players": 177,
      "modes": {
        "WALLS": 44,
        "VAMPIREZ": 54,
        "QUAKECRAFT": 11,
        "ARENA": 2,
        "PAINTBALL": 15,
        "GINGERBREAD": 16
      }
    },
    "ARCADE": {
      "players": 1377,
      "modes": {
        "PARTY": 316,
        "HOLE_IN_THE_WALL": 16,
        "DEFENDER": 44,
        "MINI_WALLS": 58,
        "SIMON_SAYS": 28,
        "ZOMBIES_BAD_BLOOD": 12,
        "HIDE_AND_SEEK_PARTY_POOPER": 19,
        "DAYONE": 76,
        "DRAW_THEIR_THING": 23,
        "ZOMBIES_ALIEN_ARCADIUM": 85,
        "ONEINTHEQUIVER": 7,
        "SOCCER": 20,
        "PVP_CTW": 147,
        "THROW_OUT": 1,
        "ENDER": 13,
        "STARWARS": 17,
        "ZOMBIES_DEAD_END": 185,
        "FARM_HUNT": 42,
        "HIDE_AND_SEEK_PROP_HUNT": 55
      }
    },
    "HOUSING": {
      "players": 2024
    },
    "BUILD_BATTLE": {
      "players": 940,
      "modes": {
        "BUILD_BATTLE_SOLO_NORMAL_LATEST": 264,
        "BUILD_BATTLE_GUESS_THE_BUILD": 112,
        "BUILD_BATTLE_TEAMS_NORMAL": 283,
        "BUILD_BATTLE_SOLO_PRO": 56,
        "BUILD_BATTLE_SOLO_NORMAL": 128
      }
    },
    "REPLAY": {
      "players": 58,
      "modes": {
        "BASE": 58
      }
    },
    "DUELS": {
      "players": 3370,
      "modes": {
        "DUELS_BOWSPLEEF_DUEL": 28,
        "DUELS_BOW_DUEL": 13,
        "DUELS_BRIDGE_2V2V2V2": 4,
        "DUELS_MW_DUEL": 16,
        "DUELS_UHC_FOUR": 31,
        "DUELS_UHC_MEETUP": 47,
        "DUELS_BRIDGE_DOUBLES": 184,
        "DUELS_SW_DOUBLES": 62,
        "DUELS_UHC_DOUBLES": 34,
        "DUELS_BRIDGE_FOUR": 88,
        "DUELS_SUMO_DUEL": 159,
        "DUELS_BRIDGE_3V3V3V3": 19,
        "DUELS_UHC_DUEL": 357,
        "DUELS_OP_DOUBLES": 17,
        "DUELS_OP_DUEL": 59,
        "DUELS_MW_DOUBLES": 4,
        "DUELS_BLITZ_DUEL": 45,
        "DUELS_POTION_DUEL": 14,
        "DUELS_CLASSIC_DUEL": 194,
        "DUELS_COMBO_DUEL": 12,
        "DUELS_BRIDGE_DUEL": 1038,
        "DUELS_SW_DUEL": 211
      }
    },
    "BATTLEGROUND": {
      "players": 80,
      "modes": {
        "ctf_mini": 4,
        "domination": 1,
        "team_deathmatch": 24
      }
    },
    "WALLS3": {
      "players": 123,
      "modes": {
        "standard": 103
      }
    },
    "PROTOTYPE": {
      "players": 468,
      "modes": {
        "TOWERWARS_SOLO": 41,
        "TOWERWARS_TEAM_OF_TWO": 26
      }
    },
    "SKYBLOCK": {
      "players": 29173,
      "modes": {
        "dungeon_hub": 1144,
        "farming_1": 321,
        "mining_2": 719,
        "mining_3": 1902,
        "crystal_hollows": 2013,
        "combat_3": 1400,
        "dynamic": 11466,
        "combat_1": 327,
        "foraging_1": 508,
        "hub": 6246,
        "combat_2": 150,
        "dungeon": 2816,
        "mining_1": 160
      }
    },
    "PIT": {
      "players": 585,
      "modes": {
        "PIT": 585
      }
    },
    "SURVIVAL_GAMES": {
      "players": 134,
      "modes": {
        "solo_normal": 71,
        "teams_normal": 37
      }
    },
    "MURDER_MYSTERY": {
      "players": 938,
      "modes": {
        "MURDER_DOUBLE_UP": 239,
        "MURDER_INFECTION": 80,
        "MURDER_ASSASSINS": 43,
        "MURDER_CLASSIC": 411
      }
    },
    "SKYWARS": {
      "players": 3171,
      "modes": {
        "ranked_normal": 135,
        "solo_insane_tnt_madness": 36,
        "solo_insane_lucky": 121,
        "solo_insane_slime": 2,
        "teams_insane_lucky": 91,
        "teams_insane": 269,
        "solo_normal": 901,
        "solo_insane": 746,
        "teams_insane_tnt_madness": 1,
        "teams_normal": 327,
        "mega_normal": 2
      }
    },
    "BEDWARS": {
      "players": 17473,
      "modes": {
        "BEDWARS_TWO_FOUR": 841,
        "BEDWARS_FOUR_THREE": 2060,
        "BEDWARS_EIGHT_ONE": 2481,
        "BEDWARS_EIGHT_TWO_RUSH": 5,
        "BEDWARS_FOUR_FOUR_ARMED": 657,
        "BEDWARS_EIGHT_TWO_ARMED": 432,
        "BEDWARS_FOUR_FOUR": 3398,
        "BEDWARS_EIGHT_TWO": 4753,
        "BEDWARS_FOUR_FOUR_ULTIMATE": 2,
        "BEDWARS_EIGHT_TWO_LUCKY": 13,
        "BEDWARS_PRACTICE": 436,
        "BEDWARS_EIGHT_TWO_ULTIMATE": 2
      }
    },
    "MCGO": {
      "players": 65,
      "modes": {
        "normal": 23,
        "deathmatch": 27
      }
    },
    "TNTGAMES": {
      "players": 684,
      "modes": {
        "PVPRUN": 9,
        "TNTAG": 330,
        "TNTRUN": 172,
        "CAPTURE": 22,
        "BOWSPLEEF": 38
      }
    },
    "SUPER_SMASH": {
      "players": 58,
      "modes": {
        "1v1_normal": 4,
        "solo_normal": 7,
        "2v2_normal": 18
      }
    },
    "LIMBO": {
      "players": 419
    },
    "IDLE": {
      "players": 7780
    },
    "QUEUE": {
      "players": 0
    }
  },
  "playerCount": 71227
}