{
  "success": true,
  "games": {
    "MAIN_LOBBY": {
      "players": 498
    },
    "TOURNAMENT_LOBBY": {
      "players": 18
    },
    "SMP": {
      "players": 1495
    },
    "SPEED_UHC": {
      "players": 33,
      "modes": {
        "team_normal": 6,
        "solo_normal": 27
      }
    },
    "UHC": {
      "players": 413,
      "modes": {
        "TEAMS": 219,
        "SOLO": 135
      }
    },
    "LEGACY": {
      "players": 225,
      "modes": {
        "WALLS": 59,
        "VAMPIREZ": 61,
        "QUAKECRAFT": 13,
        "ARENA": 1,
        "PAINTBALL": 37,
        "GINGERBREAD": 19
      }
    },
    "ARCADE": {
      "players": 1695,
      "modes": {
        "PARTY": 368,
        "HOLE_IN_THE_WALL": 14,
        "DEFENDER": 45,
        "MINI_WALLS": 51,
        "SIMON_SAYS": 58,
        "ZOMBIES_BAD_BLOOD": 34,
        "HIDE_AND_SEEK_PARTY_POOPER": 34,
        "DAYONE": 77,
        "DRAW_THEIR_THING": 50,
        "ZOMBIES_ALIEN_ARCADIUM": 107,
        "ONEINTHEQUIVER": 5,
        "SOCCER": 22,
        "PVP_CTW": 143,
        "ENDER": 9,
        "STARWARS": 21,
        "DRAGONWARS2": 1,
        "ZOMBIES_DEAD_END": 247,
        "FARM_HUNT": 81,
        "HIDE_AND_SEEK_PROP_HUNT": 82
      }
    },
    "HOUSING": {
      "players": 2161
    },
    "BUILD_BATTLE": {
      "players": 1168,
      "modes": {
        "BUILD_BATTLE_SOLO_NORMAL_LATEST": 279,
        "BUILD_BATTLE_GUESS_THE_BUILD": 135,
        "BUILD_BATTLE_TEAMS_NORMAL": 399,
        "BUILD_BATTLE_SOLO_NORMAL": 175,
        "BUILD_BATTLE_SOLO_PRO": 53
      }
    },
    "REPLAY": {
      "players": 96,
      "modes": {
        "BASE": 96
      }
    },
    "DUELS": {
      "players": 4165,
      "modes": {
        "DUELS_BOWSPLEEF_DUEL": 40,
        "DUELS_BRIDGE_2V2V2V2": 10,
        "DUELS_BOW_DUEL": 29,
        "DUELS_MW_DUEL": 10,
        "DUELS_UHC_FOUR": 24,
        "DUELS_UHC_MEETUP": 38,
        "DUELS_BRIDGE_DOUBLES": 260,
        "DUELS_SW_DOUBLES": 101,
        "DUELS_UHC_DOUBLES": 50,
        "DUELS_BRIDGE_FOUR": 112,
        "DUELS_BRIDGE_3V3V3V3": 23,
        "DUELS_SUMO_DUEL": 222,
        "DUELS_UHC_DUEL": 374,
        "DUELS_OP_DOUBLES": 37,
        "DUELS_OP_DUEL": 92,
        "DUELS_BLITZ_DUEL": 62,
        "DUELS_CLASSIC_DUEL": 227,
        "DUELS_POTION_DUEL": 11,
        "DUELS_COMBO_DUEL": 34,
        "DUELS_BRIDGE_DUEL": 1234,
        "DUELS_SW_DUEL": 326
      }
    },
    "BATTLEGROUND": {
      "players": 139,
      "modes": {
        "ctf_mini": 34,
        "domination": 48,
        "team_deathmatch": 2
      }
    },
    "WALLS3": {
      "players": 137,
      "modes": {
        "standard": 125,
        "face_off": 1
      }
    },
    "PROTOTYPE": {
      "players": 511,
      "modes": {
        "TOWERWARS_SOLO": 43,
        "TOWERWARS_TEAM_OF_TWO": 15
      }
    },
    "SKYBLOCK": {
      "players": 32442,
      "modes": {
        "dungeon_hub": 1263,
        "farming_1": 351,
        "mining_2": 896,
        "mining_3": 2069,
        "combat_3": 1643,
        "crystal_hollows": 2431,
        "dynamic": 11494,
        "combat_1": 407,
        "foraging_1": 623,
        "hub": 7380,
        "combat_2": 177,
        "dungeon": 3495,
        "mining_1": 212
      }
    },
    "PIT": {
      "players": 652,
      "modes": {
        "PIT": 653
      }
    },
    "SURVIVAL_GAMES": {
      "players": 173,
      "modes": {
        "solo_normal": 69,
        "teams_normal": 66
      }
    },
    "MURDER_MYSTERY": {
      "players": 1149,
      "modes": {
        "MURDER_DOUBLE_UP": 263,
        "MURDER_INFECTION": 131,
        "MURDER_ASSASSINS": 62,
        "MURDER_CLASSIC": 498
      }
    },
    "SKYWARS": {
      "players": 3726,
      "modes": {
        "ranked_normal": 150,
        "solo_insane_tnt_madness": 59,
        "solo_insane_lucky": 134,
        "teams_insane_lucky": 95,
        "solo_normal": 972,
        "teams_insane": 351,
        "solo_insane": 873,
        "teams_insane_tnt_madness": 1,
        "teams_normal": 370,
        "mega_normal": 30
      }
    },
    "BEDWARS": {
      "players": 21201,
      "modes": {
        "BEDWARS_TWO_FOUR": 957,
        "BEDWARS_FOUR_FOUR_RUSH": 5,
        "BEDWARS_EIGHT_ONE": 2978,
        "BEDWARS_EIGHT_TWO_RUSH": 3,
        "BEDWARS_FOUR_FOUR_ARMED": 736,
        "BEDWARS_EIGHT_TWO_ARMED": 517,
        "BEDWARS_FOUR_FOUR": 4092,
        "BEDWARS_EIGHT_TWO": 6027,
        "BEDWARS_FOUR_FOUR_ULTIMATE": 4,
        "BEDWARS_EIGHT_TWO_LUCKY": 33,
        "BEDWARS_PRACTICE": 467,
        "BEDWARS_FOUR_THREE": 2796,
        "BEDWARS_FOUR_FOUR_LUCKY": 6,
        "BEDWARS_EIGHT_TWO_ULTIMATE": 9
      }
    },
    "MCGO": {
      "players": 120,
      "modes": {
        "normal": 37,
        "normal_party": 10,
        "deathmatch": 36
      }
    },
    "TNTGAMES": {
      "players": 747,
      "modes": {
        "PVPRUN": 12,
        "TNTAG": 316,
        "TNTRUN": 216,
        "BOWSPLEEF": 38,
        "CAPTURE": 36
      }
    },
    "SUPER_SMASH": {
      "players": 62,
      "modes": {
        "1v1_normal": 3,
        "solo_normal": 13,
        "2v2_normal": 19
      }
    },
    "LIMBO": {
      "players": 401
    },
    "IDLE": {
      "players": 9095
    },
    "QUEUE": {
      "players": 0
    }
  },
  "playerCount": 82492
}