{
  "success": true,
  "games": {
    "MAIN_LOBBY": {
      "players": 538
    },
    "TOURNAMENT_LOBBY": {
      "players": 19
    },
    "SMP": {
      "players": 1911
    },
    "SPEED_UHC": {
      "players": 45,
      "modes": {
        "team_normal": 18,
        "solo_normal": 27
      }
    },
    "UHC": {
      "players": 340,
      "modes": {
        "TEAMS": 155,
        "SOLO": 128
      }
    },
    "LEGACY": {
      "players": 268,
      "modes": {
        "WALLS": 58,
        "VAMPIREZ": 74,
        "QUAKECRAFT": 9,
        "ARENA": 6,
        "PAINTBALL": 41,
        "GINGERBREAD": 29
      }
    },
    "ARCADE": {
      "players": 2129,
      "modes": {
        "PARTY": 485,
        "HOLE_IN_THE_WALL": 29,
        "DEFENDER": 41,
        "MINI_WALLS": 69,
        "SIMON_SAYS": 69,
        "ZOMBIES_BAD_BLOOD": 39,
        "HIDE_AND_SEEK_PARTY_POOPER": 42,
        "DAYONE": 105,
        "DRAW_THEIR_THING": 43,
        "ZOMBIES_ALIEN_ARCADIUM": 123,
        "ONEINTHEQUIVER": 21,
        "SOCCER": 52,
        "PVP_CTW": 213,
        "THROW_OUT": 10,
        "ENDER": 18,
        "STARWARS": 27,
        "DRAGONWARS2": 20,
        "ZOMBIES_DEAD_END": 263,
        "FARM_HUNT": 82,
        "HIDE_AND_SEEK_PROP_HUNT": 93
      }
    },
    "HOUSING": {
      "players": 2931
    },
    "BUILD_BATTLE": {
      "players": 1408,
      "modes": {
        "BUILD_BATTLE_SOLO_NORMAL_LATEST": 292,
        "BUILD_BATTLE_GUESS_THE_BUILD": 141,
        "BUILD_BATTLE_TEAMS_NORMAL": 486,
        "BUILD_BATTLE_SOLO_PRO": 104,
        "BUILD_BATTLE_SOLO_NORMAL": 188
      }
    },
    "REPLAY": {
      "players": 91,
      "modes": {
        "BASE": 91
      }
    },
    "DUELS": {
      "players": 5235,
      "modes": {
        "DUELS_BOWSPLEEF_DUEL": 47,
        "DUELS_BRIDGE_2V2V2V2": 9,
        "DUELS_BOW_DUEL": 21,
        "DUELS_UHC_FOUR": 45,
        "DUELS_MW_DUEL": 31,
        "DUELS_UHC_MEETUP": 58,
        "DUELS_BRIDGE_DOUBLES": 351,
        "DUELS_SW_DOUBLES": 120,
        "DUELS_UHC_DOUBLES": 69,
        "DUELS_BRIDGE_FOUR": 162,
        "DUELS_BRIDGE_3V3V3V3": 17,
        "DUELS_SUMO_DUEL": 259,
        "DUELS_UHC_DUEL": 373,
        "DUELS_OP_DOUBLES": 39,
        "DUELS_OP_DUEL": 93,
        "DUELS_MW_DOUBLES": 2,
        "DUELS_BLITZ_DUEL": 49,
        "DUELS_POTION_DUEL": 31,
        "DUELS_CLASSIC_DUEL": 336,
        "DUELS_COMBO_DUEL": 57,
        "DUELS_BRIDGE_DUEL": 1646,
        "DUELS_SW_DUEL": 374
      }
    },
    "BATTLEGROUND": {
      "players": 131,
      "modes": {
        "ctf_mini": 22,
        "domination": 47,
        "team_deathmatch": 2
      }
    },
    "WALLS3": {
      "players": 166,
      "modes": {
        "standard": 143,
        "face_off": 1
      }
    },
    "PROTOTYPE": {
      "players": 554,
      "modes": {
        "TOWERWARS_SOLO": 51,
        "TOWERWARS_TEAM_OF_TWO": 48
      }
    },
    "SKYBLOCK": {
      "players": 37944,
      "modes": {
        "dungeon_hub": 1501,
        "farming_1": 376,
        "mining_2": 1019,
        "dark_auction": 236,
        "mining_3": 2537,
        "crystal_hollows": 2415,
        "combat_3": 1831,
        "dynamic": 14227,
        "combat_1": 417,
        "foraging_1": 690,
        "hub": 8422,
        "combat_2": 227,
        "dungeon": 3819,
        "mining_1": 228
      }
    },
    "PIT": {
      "players": 648,
      "modes": {
        "PIT": 648
      }
    },
    "SURVIVAL_GAMES": {
      "players": 201,
      "modes": {
        "solo_normal": 87,
        "teams_normal": 83
      }
    },
    "MURDER_MYSTERY": {
      "players": 1367,
      "modes": {
        "MURDER_DOUBLE_UP": 373,
        "MURDER_INFECTION": 167,
        "MURDER_ASSASSINS": 65,
        "MURDER_CLASSIC": 530
      }
    },
    "SKYWARS": {
      "players": 4664,
      "modes": {
        "ranked_normal": 161,
        "solo_insane_tnt_madness": 61,
        "solo_insane_lucky": 168,
        "teams_insane_lucky": 124,
        "teams_insane": 500,
        "solo_normal": 1135,
        "solo_insane_hunters_vs_beasts": 11,
        "solo_insane": 1191,
        "teams_insane_tnt_madness": 17,
        "teams_normal": 458,
        "mega_normal": 60
      }
    },
    "BEDWARS": {
      "players": 25552,
      "modes": {
        "BEDWARS_TWO_FOUR": 981,
        "BEDWARS_EIGHT_ONE": 3572,
        "BEDWARS_EIGHT_TWO_VOIDLESS": 2,
        "BEDWARS_FOUR_FOUR_ARMED": 921,
        "BEDWARS_EIGHT_TWO_ARMED": 666,
        "BEDWARS_FOUR_FOUR": 4235,
        "BEDWARS_EIGHT_TWO": 7804,
        "BEDWARS_PRACTICE": 553,
        "BEDWARS_EIGHT_TWO_LUCKY": 58,
        "BEDWARS_FOUR_FOUR_VOIDLESS": 2,
        "BEDWARS_FOUR_THREE": 3353,
        "BEDWARS_FOUR_FOUR_LUCKY": 8,
        "BEDWARS_EIGHT_TWO_ULTIMATE": 2
      }
    },
    "MCGO": {
      "players": 131,
      "modes": {
        "normal": 55,
        "deathmatch": 56
      }
    },
    "TNTGAMES": {
      "players": 974,
      "modes": {
        "PVPRUN": 33,
        "TNTAG": 450,
        "TNTRUN": 234,
        "BOWSPLEEF": 61,
        "CAPTURE": 52
      }
    },
    "SUPER_SMASH": {
      "players": 93,
      "modes": {
        "1v1_normal": 19,
        "solo_normal": 22,
        "2v2_normal": 14,
        "teams_normal": 10
      }
    },
    "LIMBO": {
      "players": 411
    },
    "IDLE": {
      "players": 9523
    },
    "QUEUE": {
      "players": 0
    }
  },
  "playerCount": 97216
}