{
  "success": true,
  "games": {
    "MAIN_LOBBY": {
      "players": 582
    },
    "TOURNAMENT_LOBBY": {
      "players": 6
    },
    "SMP": {
      "players": 1494
    },
    "HOUSING": {
      "players": 2294
    },
    "PIT": {
      "players": 518,
      "modes": {
        "PIT": 518
      }
    },
    "TNTGAMES": {
      "players": 703,
      "modes": {
        "PVPRUN": 10,
        "TNTAG": 346,
        "TNTRUN": 165,
        "BOWSPLEEF": 38,
        "CAPTURE": 25
      }
    },
    "REPLAY": {
      "players": 79,
      "modes": {
        "BASE": 79
      }
    },
    "SURVIVAL_GAMES": {
      "players": 174,
      "modes": {
        "solo_normal": 74,
        "teams_normal": 70
      }
    },
    "BEDWARS": {
      "players": 20664,
      "modes": {
        "BEDWARS_TWO_FOUR": 831,
        "BEDWARS_FOUR_THREE": 2508,
        "BEDWARS_FOUR_FOUR_LUCKY": 4,
        "BEDWARS_EIGHT_ONE": 2931,
        "BEDWARS_EIGHT_TWO_RUSH": 2,
        "BEDWARS_FOUR_FOUR_ARMED": 675,
        "BEDWARS_EIGHT_TWO_ARMED": 549,
        "BEDWARS_FOUR_FOUR": 3443,
        "BEDWARS_EIGHT_TWO": 6250,
        "BEDWARS_PRACTICE": 416,
        "BEDWARS_EIGHT_TWO_LUCKY": 47,
        "BEDWARS_EIGHT_TWO_ULTIMATE": 3
      }
    },
    "SUPER_SMASH": {
      "players": 44,
      "modes": {
        "1v1_normal": 1,
        "friends_normal": 4,
        "solo_normal": 7,
        "2v2_normal": 9,
        "teams_normal": 5
      }
    },
    "SKYBLOCK": {
      "players": 31768,
      "modes": {
        "dungeon_hub": 1277,
        "farming_1": 338,
        "mining_2": 856,
        "dark_auction": 106,
        "mining_3": 2186,
        "combat_3": 1556,
        "crystal_hollows": 2239,
        "dynamic": 11998,
        "combat_1": 343,
        "foraging_1": 560,
        "hub": 7078,
        "combat_2": 173,
        "dungeon": 2873,
        "mining_1": 186
      }
    },
    "MURDER_MYSTERY": {
      "players": 1060,
      "modes": {
        "MURDER_DOUBLE_UP": 242,
        "MURDER_INFECTION": 110,
        "MURDER_ASSASSINS": 62,
        "MURDER_CLASSIC": 451
      }
    },
    "LEGACY": {
      "players": 206,
      "modes": {
        "GINGERBREAD": 16,
        "QUAKECRAFT": 8,
        "WALLS": 53,
        "VAMPIREZ": 58,
        "ARENA": 1,
        "PAINTBALL": 21
      }
    },
    "SKYWARS": {
      "players": 3693,
      "modes": {
        "ranked_normal": 126,
        "solo_insane_tnt_madness": 61,
        "solo_insane_lucky": 117,
        "solo_insane_slime": 2,
        "teams_insane_lucky": 97,
        "teams_insane": 298,
        "solo_normal": 1018,
        "solo_insane": 820,
        "teams_insane_tnt_madness": 3,
        "teams_normal": 418,
        "mega_normal": 16
      }
    },
    "UHC": {
      "players": 234,
      "modes": {
        "TEAMS": 110,
        "SOLO": 90
      }
    },
    "ARCADE": {
      "players": 1618,
      "modes": {
        "PARTY": 398,
        "HOLE_IN_THE_WALL": 13,
        "DEFENDER": 40,
        "MINI_WALLS": 58,
        "SIMON_SAYS": 59,
        "ZOMBIES_BAD_BLOOD": 33,
        "HIDE_AND_SEEK_PARTY_POOPER": 20,
        "DAYONE": 82,
        "DRAW_THEIR_THING": 33,
        "ZOMBIES_ALIEN_ARCADIUM": 79,
        "ONEINTHEQUIVER": 9,
        "SOCCER": 28,
        "PVP_CTW": 141,
        "ENDER": 18,
        "STARWARS": 1,
        "DRAGONWARS2": 12,
        "ZOMBIES_DEAD_END": 191,
        "HIDE_AND_SEEK_PROP_HUNT": 68,
        "FARM_HUNT": 82
      }
    },
    "SPEED_UHC": {
      "players": 36,
      "modes": {
        "team_normal": 19,
        "solo_normal": 17
      }
    },
    "BUILD_BATTLE": {
      "players": 1126,
      "modes": {
        "BUILD_BATTLE_HALLOWEEN": 12,
        "BUILD_BATTLE_SOLO_NORMAL_LATEST": 254,
        "BUILD_BATTLE_GUESS_THE_BUILD": 131,
        "BUILD_BATTLE_TEAMS_NORMAL": 384,
        "BUILD_BATTLE_SOLO_PRO": 59,
        "BUILD_BATTLE_SOLO_NORMAL": 144
      }
    },
    "DUELS": {
      "players": 4300,
      "modes": {
        "DUELS_BOWSPLEEF_DUEL": 42,
        "DUELS_BOW_DUEL": 14,
        "DUELS_BRIDGE_2V2V2V2": 3,
        "DUELS_MW_DUEL": 16,
        "DUELS_UHC_FOUR": 34,
        "DUELS_UHC_MEETUP": 42,
        "DUELS_BRIDGE_DOUBLES": 249,
        "DUELS_SW_DOUBLES": 102,
        "DUELS_UHC_DOUBLES": 52,
        "DUELS_BRIDGE_FOUR": 91,
        "DUELS_BRIDGE_3V3V3V3": 24,
        "DUELS_SUMO_DUEL": 238,
        "DUELS_UHC_DUEL": 283,
        "DUELS_OP_DOUBLES": 29,
        "DUELS_OP_DUEL": 89,
        "DUELS_MW_DOUBLES": 9,
        "DUELS_BLITZ_DUEL": 59,
        "DUELS_POTION_DUEL": 13,
        "DUELS_CLASSIC_DUEL": 209,
        "DUELS_BRIDGE_DUEL": 1390,
        "DUELS_COMBO_DUEL": 44,
        "DUELS_SW_DUEL": 378
      }
    },
    "PROTOTYPE": {
      "players": 422,
      "modes": {
        "TOWERWARS_SOLO": 39,
        "TOWERWARS_TEAM_OF_TWO": 17
      }
    },
    "BATTLEGROUND": {
      "players": 114,
      "modes": {
        "ctf_mini": 51,
        "domination": 4,
        "team_deathmatch": 8
      }
    },
    "MCGO": {
      "players": 112,
      "modes": {
        "normal": 45,
        "normal_party": 11,
        "deathmatch": 27
      }
    },
    "WALLS3": {
      "players": 112,
      "modes": {
        "standard": 103
      }
    },
    "LIMBO": {
      "players": 372
    },
    "IDLE": {
      "players": 8612
    },
    "QUEUE": {
      "players": 0
    }
  },
  "playerCount": 80387
}